torch_cluster/__init__.py
torch_cluster/_fps_cpu.so
torch_cluster/_fps_cuda.so
torch_cluster/_graclus_cpu.so
torch_cluster/_graclus_cuda.so
torch_cluster/_grid_cpu.so
torch_cluster/_grid_cuda.so
torch_cluster/_knn_cpu.so
torch_cluster/_knn_cuda.so
torch_cluster/_nearest_cpu.so
torch_cluster/_nearest_cuda.so
torch_cluster/_radius_cpu.so
torch_cluster/_radius_cuda.so
torch_cluster/_rw_cpu.so
torch_cluster/_rw_cuda.so
torch_cluster/_sampler_cpu.so
torch_cluster/_sampler_cuda.so
torch_cluster/_version_cpu.so
torch_cluster/_version_cuda.so
torch_cluster/fps.py
torch_cluster/graclus.py
torch_cluster/grid.py
torch_cluster/knn.py
torch_cluster/nearest.py
torch_cluster/radius.py
torch_cluster/rw.py
torch_cluster/sampler.py
torch_cluster/testing.py
torch_cluster/typing.py
torch_cluster_rocm-1.6.3.post2.dist-info/LICENSE
torch_cluster_rocm-1.6.3.post2.dist-info/METADATA
torch_cluster_rocm-1.6.3.post2.dist-info/RECORD
torch_cluster_rocm-1.6.3.post2.dist-info/WHEEL
torch_cluster_rocm-1.6.3.post2.dist-info/top_level.txt