Metadata-Version: 2.1
Name: torch-cluster-rocm
Version: 1.6.3.post2
Summary: PyTorch Extension Library of Optimized Graph Cluster Algorithms (ROCm Build)
Home-page: https://github.com/Looong01/pyg-rocm-build
Download-URL: https://github.com/Looong01/pyg-rocm-build/releases
Author: Looong
Author-email: lizelongdd@hotmail.com, matthias.fey@tu-dortmund.de
License: MIT
Platform: manylinux_2_32_x86_64
Requires-Python: >=3.8
